djangocms_apphook_setup/__init__.py
djangocms_apphook_setup/base.py
djangocms_apphook_setup-0.5.1.dist-info/LICENSE
djangocms_apphook_setup-0.5.1.dist-info/METADATA
djangocms_apphook_setup-0.5.1.dist-info/WHEEL
djangocms_apphook_setup-0.5.1.dist-info/top_level.txt
djangocms_apphook_setup-0.5.1.dist-info/RECORD
