Metadata-Version: 2.1
Name: djangocms-apphook-setup
Version: 0.5.1
Summary: Library to auto setup apphooks
Home-page: https://github.com/nephila/djangocms-apphook-setup
Author: Iacopo Spalletti
Author-email: i.spalletti@nephila.it
License: BSD
Keywords: djangocms-apphook-setup,django CMS,apphook
Classifier: Intended Audience :: Developers
Classifier: License :: OSI Approved :: BSD License
Classifier: Development Status :: 5 - Production/Stable
Classifier: Framework :: Django
Classifier: Framework :: Django :: 3.2
Classifier: Framework :: Django :: 4.1
Classifier: Framework :: Django :: 4.2
Classifier: Programming Language :: Python
Classifier: Programming Language :: Python :: 3
Classifier: Programming Language :: Python :: 3.7
Classifier: Programming Language :: Python :: 3.8
Classifier: Programming Language :: Python :: 3.9
Classifier: Programming Language :: Python :: 3.10
Classifier: Programming Language :: Python :: 3.11
Requires-Python: >=3.7
License-File: LICENSE
Requires-Dist: django-cms <4.0,>=3.7
